joao_marcionilo_contratos_governamentais/__init__.py
joao_marcionilo_contratos_governamentais-0.1.0.dist-info/METADATA
joao_marcionilo_contratos_governamentais-0.1.0.dist-info/WHEEL
joao_marcionilo_contratos_governamentais-0.1.0.dist-info/licenses/LICENSE
joao_marcionilo_contratos_governamentais-0.1.0.dist-info/RECORD
