Metadata-Version: 2.4
Name: joao_marcionilo_contratos_governamentais
Version: 0.1.0
Summary: Agrupa os datasets para uma análise das contratações dos órgãos e entidades da administração pública direta, autárquica e fundacional obtidos através do site: https://portaldatransparencia.gov.br/download-de-dados/compras
Project-URL: Repository, https://github.com/Joao-Marcionilo/contratos-governamentais
Author-email: João Marcionilo <marcionilojob@gmail.com>
License-File: LICENSE
Classifier: License :: OSI Approved :: MIT License
Classifier: Programming Language :: Python :: 3
Requires-Python: >=3.12
Requires-Dist: pandas~=2.2.3
Requires-Dist: pyodbc~=5.2.0
